zenyxheic/__init__.py
zenyxheic/__main__.py
zenyxheic-1.1.0.dist-info/METADATA
zenyxheic-1.1.0.dist-info/WHEEL
zenyxheic-1.1.0.dist-info/licenses/LICENSE
zenyxheic-1.1.0.dist-info/RECORD
