Metadata-Version: 2.1
Name: zenyxheic
Version: 1.1.0
Summary: Convert HEIC files to jpg, png, gif
Project-URL: Homepage, https://github.com/neunyx/zenyxheic
Project-URL: Issues, https://github.com/neunyx/zenyxheic/issues
Author-email: zewenn <zc.fallens@gamil.com>
License-File: LICENSE
Classifier: License :: OSI Approved :: MIT License
Classifier: Operating System :: OS Independent
Classifier: Programming Language :: Python :: 3
Requires-Python: >=3.7
